MANIFEST.in
README.md
setup.py
noseenv/__init__.py
noseenv/tests.py
noseenv.egg-info/PKG-INFO
noseenv.egg-info/SOURCES.txt
noseenv.egg-info/dependency_links.txt
noseenv.egg-info/entry_points.txt
noseenv.egg-info/requires.txt
noseenv.egg-info/top_level.txt