Metadata-Version: 1.1
Name: noseenv
Version: 0.0.0
Summary: Nose plugin to add options of the form "--env ENVIRONMENT_VARIABLE=VALUE"
Home-page: http://github.com/msabramo/python-noseenv
Author: Marc Abramowitz
Author-email: marc@marc-abramowitz.com
License: GPL
Platform: UNKNOWN
Classifier: Development Status :: 5 - Production/Stable
Classifier: Environment :: Console
Classifier: Intended Audience :: Developers
Classifier: Natural Language :: English
Classifier: License :: OSI Approved :: GNU General Public License (GPL)
Classifier: Operating System :: OS Independent
Classifier: Programming Language :: Python :: 2
Classifier: Programming Language :: Python :: 2.5
Classifier: Programming Language :: Python :: 2.6
Classifier: Programming Language :: Python :: 2.7
Classifier: Topic :: Software Development :: Testing
